inteliver/__init__.py
inteliver/alembic.ini
inteliver/constants.py
inteliver/main.py
inteliver/version.py
inteliver/alembic/README
inteliver/alembic/env.py
inteliver/alembic/script.py.mako
inteliver/alembic/versions/4056a4a49e98_initial_migration.py
inteliver/auth/__init__.py
inteliver/auth/constants.py
inteliver/auth/exceptions.py
inteliver/auth/router.py
inteliver/auth/schemas.py
inteliver/auth/service.py
inteliver/auth/utils.py
inteliver/cli/__init__.py
inteliver/cli/main.py
inteliver/cli/minio.py
inteliver/cli/postgres.py
inteliver/cli/user.py
inteliver/cli/utils.py
inteliver/config/__init__.py
inteliver/config/config.py
inteliver/config/schema.py
inteliver/config/utils.py
inteliver/config/yamls/config.dev.docker.yml
inteliver/config/yamls/config.dev.standalone.yml
inteliver/config/yamls/config.prod.yml
inteliver/config/yamls/config.stage.yml
inteliver/database/__init__.py
inteliver/database/dependencies.py
inteliver/database/postgres.py
inteliver/errors/__init__.py
inteliver/errors/error.py
inteliver/image/__init__.py
inteliver/image/exceptions.py
inteliver/image/image_processor.py
inteliver/image/object_detection.py
inteliver/image/router.py
inteliver/image/service.py
inteliver/routers/__init__.py
inteliver/storage/__init__.py
inteliver/storage/constants.py
inteliver/storage/exceptions.py
inteliver/storage/router.py
inteliver/storage/schemas.py
inteliver/storage/service.py
inteliver/users/__init__.py
inteliver/users/crud.py
inteliver/users/exceptions.py
inteliver/users/models.py
inteliver/users/router.py
inteliver/users/schemas.py
inteliver/users/service.py
inteliver/users/utils.py
inteliver/utils/__init__.py
inteliver/utils/i18n.py
inteliver/utils/lifespan.py
inteliver/utils/logger.py
inteliver/utils/middleware.py
inteliver/versioning/__init__.py
inteliver/versioning/router.py
inteliver/versioning/schemas.py
inteliver-0.5.0.dist-info/LICENSE.txt
inteliver-0.5.0.dist-info/METADATA
inteliver-0.5.0.dist-info/WHEEL
inteliver-0.5.0.dist-info/entry_points.txt
inteliver-0.5.0.dist-info/top_level.txt
inteliver-0.5.0.dist-info/RECORD
