Metadata-Version: 2.1
Name: inteliver
Version: 0.5.0
Summary: inteliver, high performance, ready for production, image management.
Author-email: "A. Lavasani" <amirm.lavasani@gmail.com>
Maintainer-email: "A. Lavasani" <amirm.lavasani@gmail.com>
License: BSD 2-Clause License
Project-URL: Homepage, https://github.com/inteliver/inteliver
Project-URL: Bug Tracker, https://github.com/inteliver/inteliver/issues
Project-URL: Documentation, https://inteliver.github.io/inteliver/
Project-URL: Source, https://github.com/inteliver/inteliver
Keywords: ai,service,template,api,docker
Classifier: Development Status :: 3 - Alpha
Classifier: Intended Audience :: Developers
Classifier: Topic :: Software Development :: Build Tools
Classifier: License :: OSI Approved :: MIT License
Classifier: Programming Language :: Python :: 3
Classifier: Programming Language :: Python :: 3.7
Classifier: Programming Language :: Python :: 3.8
Classifier: Programming Language :: Python :: 3.9
Classifier: Programming Language :: Python :: 3.10
Classifier: Programming Language :: Python :: 3.11
Classifier: Programming Language :: Python :: 3 :: Only
Requires-Python: >=3.10
License-File: LICENSE.txt
Requires-Dist: alembic==1.13.2
Requires-Dist: art==6.1
Requires-Dist: asyncpg==0.29.0
Requires-Dist: babel==2.14.0
Requires-Dist: colorama==0.4.6
Requires-Dist: dlib==19.24.5
Requires-Dist: fastapi==0.109.1
Requires-Dist: loguru==0.7.2
Requires-Dist: minio==7.2.7
Requires-Dist: numpy==1.26.4
Requires-Dist: opencv-python==4.10.0.84
Requires-Dist: bcrypt==4.1.3
Requires-Dist: pillow==10.4.0
Requires-Dist: psycopg2-binary==2.9.9
Requires-Dist: pydantic-settings==2.2.1
Requires-Dist: pydantic[email]==2.5.1
Requires-Dist: pyjwt==2.8.0
Requires-Dist: python-jose[cryptography]==3.3.0
Requires-Dist: python-multipart==0.0.9
Requires-Dist: pyyaml==6.0.2
Requires-Dist: sqlalchemy==2.0.31
Requires-Dist: tabulate==0.9.0
Requires-Dist: typer==0.12.3
Requires-Dist: uvicorn==0.24.0.post1
Provides-Extra: dev
Requires-Dist: black==24.3.0; extra == "dev"
Requires-Dist: build==1.0.3; extra == "dev"
Requires-Dist: flake8==6.1.0; extra == "dev"
Requires-Dist: httpx==0.25.1; extra == "dev"
Requires-Dist: mypy==1.7.0; extra == "dev"
Requires-Dist: pdoc3==0.10.0; extra == "dev"
Requires-Dist: pygount==1.6.1; extra == "dev"
Requires-Dist: pytest-cov==4.1.0; extra == "dev"
Requires-Dist: pytest==7.4.3; extra == "dev"
Requires-Dist: python-semantic-release==8.7.0; extra == "dev"
Requires-Dist: ruff==0.4.1; extra == "dev"
